linq/__init__.py
linq/core/__init__.py
linq/core/collections.py
linq/core/flow.py
linq/core/flow.pyi
linq/core/utils.py
linq/standard/__init__.py
linq/standard/_helper.py
linq/standard/dict.py
linq/standard/general.py
linq/standard/generator.py
linq/standard/list.py
linq/standard/set.py
linq_t-0.1.dist-info/DESCRIPTION.rst
linq_t-0.1.dist-info/METADATA
linq_t-0.1.dist-info/RECORD
linq_t-0.1.dist-info/WHEEL
linq_t-0.1.dist-info/metadata.json
linq_t-0.1.dist-info/top_level.txt
