Metadata-Version: 2.0
Name: linq-t
Version: 0.1
Summary: Language Integrated Query for Python
Home-page: https://github.com/Xython/Linq.py
Author: thautwarm
Author-email: twshere@outlook.com
License: MIT
Keywords: Linq,type hinting,type inference
Platform: UNKNOWN
Classifier: Programming Language :: Python :: 3.4
Classifier: Programming Language :: Python :: 3.5
Classifier: Programming Language :: Python :: 3.6
Classifier: Programming Language :: Python :: 3.7
Classifier: Programming Language :: Python :: Implementation :: CPython
